{
    "companyName": "Carroll & Turner PSC - Monticello, KY",
    "address1": "56 Court St.",
    "address2": "",
    "city": "Monticello",
    "state": "KY",
    "zip": "42633",
    "website": "https://www.carroll-turner.com",
    "phone": "606-930-4434",
    "fax": "606-348-3459",
    "profilePhotoUrl": "https://images.findlawresources.com/env_prod/type_profile/firmwld_1642434/pid_1/carroll_turner_psc.jpg",
    "moreBlocks": [
        {
            "practiceAreas": "Car Accidents"
        },
        {
            "offersFreeInitialConsultation": "Yes"
        },
        {
            "acceptsCreditCards": "<p>Yes</p>"
        },
        {
            "websites": "<a rel=\"sponsored\" target=\"new\" class=\"profile-website-body\" href=\"https://www.carroll-turner.com?refPageViewId=6bd946f912170359\"> https://www.carroll-turner.com </a>"
        },
        {
            "lawyersAtCarroll&TurnerPSCSelectedForASuperLawyers®List": "<ul><li> Carroll, Thomas E. <a href=\"/profile/lawyer/thomas-e-carroll/ky/monticello/Mjg1OTM3Ml8x/PP#feedback\">On a Super Lawyers® List</a></li></ul>"
        },
        {
            "articles": "<ul><li><a rel=\"ugc\" href=\"http://www.carroll-turner.com/Personal-Injury/\">Personal Injury</a><br></li><li><a rel=\"ugc\" href=\"http://www.carroll-turner.com/Employment-Discrimination-And-Harassment.shtml\">Employment Discrimination &amp; Harassment</a><br></li><li><a rel=\"ugc\" href=\"http://www.carroll-turner.com/Criminal-Law.shtml\">Criminal Law</a><br></li></ul>"
        }
    ],
    "practiceAreas": "Car Accidents",
    "litigation": "",
    "languages": "",
    "classesAndSeminars": "",
    "offersFreeInitialConsultation": "Yes",
    "officeHours": "",
    "honors": "",
    "articles": "<ul><li><a rel=\"ugc\" href=\"http://www.carroll-turner.com/Personal-Injury/\">Personal Injury</a><br></li><li><a rel=\"ugc\" href=\"http://www.carroll-turner.com/Employment-Discrimination-And-Harassment.shtml\">Employment Discrimination &amp; Harassment</a><br></li><li><a rel=\"ugc\" href=\"http://www.carroll-turner.com/Criminal-Law.shtml\">Criminal Law</a><br></li></ul>",
    "social_fb": "",
    "social_twitter": "",
    "social_linkedin": "",
    "social_instagram": "",
    "scrapeUrl": "https://lawyers.findlaw.com/profile/lawfirm/carroll--turner-psc/ky/monticello/MTY0MjQzNF8x/PP?refPageViewId=6bd9467ae300030a",
    "description": "<p>When you have been injured in an accident, you need to secure legal representation you can put your faith in. The personal injury lawyers of Carroll &amp; Turner PSC, in Monticello, have more than 45 years of combined experience fighting to help those who have been injured.</p><h2>How Will You Deal With The Difficulties Caused By Your Accident? &nbsp;Are Insurance Companies Treating you Unfairly?</h2><p>Too often, people come out of accidents with serious injuries that have huge impacts on their lives. They may not be able to work. They may not be able to provide care to their children or other loved ones. They may need extensive medical care.</p><p>People often do not know how to respond to all of these needs. The simple fact is that compensation is essential for helping people overcome the obstacles their injuries have created. Whoever caused your injuries should be held accountable and should fully compensate you for all of the ways they have harmed you.</p><p>Our attorneys have won multimillion-dollar verdicts, the largest at $20 million. We have been able to generate these results for our clients by providing highly effective representation.</p><p>You do not have to face the challenges caused by your accident without support you can depend on. The personal injury attorneys of Carroll &amp; Turner PSC are committed to helping people just like you through the most difficult times. To schedule a free initial consultation, call&nbsp;<span id=\"loc:1134287212\">606-536-4133</span>.</p><p>We only collect attorney fees if we secure compensation for you.</p>"
}