{
    "companyName": "Oxendine Barnes & Associates PLLC - Raleigh, NC",
    "address1": "6500 Creedmoor Road",
    "address2": "Suite 212",
    "city": "Raleigh",
    "state": "NC",
    "zip": "27613",
    "website": "http://www.oxendinebarnes.com/",
    "phone": "919-848-4333",
    "fax": "919-848-4707",
    "profilePhotoUrl": "https://images.findlawresources.com/env_prod/type_profile/firmwld_5017012/pid_1/oxendine_barnes_associates_pllc.jpg",
    "moreBlocks": [
        {
            "practiceAreas": "Personal Injury|Workers' Compensation|Litigation|Business Law"
        },
        {
            "offersFreeInitialConsultation": "Yes"
        },
        {
            "acceptsCreditCards": "<p>Yes</p>"
        },
        {
            "websites": "<a rel=\"sponsored\" href=\"http://www.oxendinebarnes.com/?refPageViewId=6c3a0936d0862233\" class=\"profile-website-body\" target=\"new\"> http://www.oxendinebarnes.com/ </a>"
        }
    ],
    "practiceAreas": "Personal Injury|Workers' Compensation|Litigation|Business Law",
    "litigation": "",
    "languages": "",
    "classesAndSeminars": "",
    "offersFreeInitialConsultation": "Yes",
    "officeHours": "",
    "honors": "",
    "articles": "",
    "social_fb": "",
    "social_twitter": "",
    "social_linkedin": "",
    "social_instagram": "",
    "scrapeUrl": "https://lawyers.findlaw.com/profile/lawfirm/oxendine-barnes--associates-pllc/nc/raleigh/NTAxNzAxMl8x/PP?refPageViewId=6c3a08a627ce09a2",
    "description": "<p>Handling a variety of litigation matters, including personal injury and business law issues, our team at Oxendine Barnes &amp; Associates PLLC in Raleigh, North Carolina, is known for returning exceptional results. Our law office has represented countless victims of car accidents, workplace injuries, medical malpractice and nursing home abuse, obtaining awards through settlement and negotiations. We are also adept at navigating the state’s workers’ compensation system.</p><p>The attorneys at our law office are members of prestigious organizations such as the Million Dollar Advocates Forum and the North Carolina Bar Association’s Litigation and Workers’ Compensation sections. Attorney Ryan D. Oxendine has been listed in The National Trial Lawyers: Top 100. Fellow attorney Jim Barnes brings years of experience in representing insurance companies to our practice, which is invaluable in anticipating the path a case may take. We have appeared on behalf of clients before state, federal and appellate courts.</p><p>Every case we take on begins with a free initial consultation at our law office. We then cater the legal strategy we develop to the needs of each client, ensuring that they feel their concerns have been addressed. In addition to our litigation practice, we also offer services in estate and tax planning. At Oxendine Barnes &amp; Associates PLLC, we accept credit cards.</p><p>&nbsp;</p><p>&nbsp;</p>"
}