{
    "companyName": "Marin and Barrett, Inc. - Woodbridge, CT",
    "address1": "1 Bradley Road",
    "address2": "Suite 201",
    "city": "Woodbridge",
    "state": "CT",
    "zip": "06525",
    "website": "https://www.marinbarrettlaw.com/connecticutpersonalinjury",
    "phone": "203-285-8167",
    "fax": "",
    "profilePhotoUrl": "https://images.findlawresources.com/env_prod/type_profile/firmwld_5201500/pid_1/marin_and_barrett_inc.jpg",
    "moreBlocks": [
        {
            "practiceAreas": "Personal Injury 100%"
        },
        {
            "litigation": "<ul><li>100%</li></ul>"
        },
        {
            "offersFreeInitialConsultation": "Yes"
        },
        {
            "acceptsCreditCards": "<p>Yes</p>"
        },
        {
            "officeHours": "<p> 24 x 7 <br></p>"
        },
        {
            "websites": "<a rel=\"sponsored\" href=\"https://www.marinbarrettlaw.com/connecticutpersonalinjury?refPageViewId=6bb1b9c1112202d6\" class=\"profile-website-body\" target=\"new\"> https://www.marinbarrettlaw.com/connecticutpersonalinjury </a><a rel=\"sponsored\" target=\"new\" class=\"profile-website-body\" href=\"https://www.marinbarrettlaw.com/connecticutslipfallattorney?refPageViewId=6bb1b9c1112202d6\"> https://www.marinbarrettlaw.com/connecticutslipfallattorney </a>"
        },
        {
            "otherOffices": "<p><a href=\"/profile/view/5048393_1\"> Marin and Barrett, Inc. </a><span class=\"pp_card_street\"> 36 South County Commons Way </span><span class=\"pp_card_street\"> Unit C-3 </span><span class=\"pp_card_street\"><span>South Kingstown</span>, <span>RI</span><span> 02879 </span></span><span class=\"pp_card_street\"> 401-519-6800 </span></p><p><a href=\"/profile/lawfirm/marin-and-barrett-inc/ri/east-greenwich/NDEwMjAyM18x/PP\"> Marin and Barrett, Inc. </a> (Main Office) <span class=\"pp_card_street\"> 58 Main Street </span><span class=\"pp_card_street\"><span>East Greenwich</span>, <span>RI</span><span> 02818 </span></span><span class=\"pp_card_street\"> 401-519-6800 </span></p><p><a href=\"/profile/view/5240059_1\"> Marin and Barrett, Inc. </a><span class=\"pp_card_street\"> 1000 Chapel View Blvd </span><span class=\"pp_card_street\"> Suite 260 </span><span class=\"pp_card_street\"><span>Cranston</span>, <span>RI</span><span> 02920 </span></span><span class=\"pp_card_street\"> 401-228-8271 </span></p><p><a href=\"/profile/view/5048394_1\"> Marin and Barrett, Inc. </a><span class=\"pp_card_street\"> 37 Bellevue Ave </span><span class=\"pp_card_street\"><span>Newport</span>, <span>RI</span><span> 02840 </span></span><span class=\"pp_card_street\"> 401-519-6800 </span></p><p><a href=\"/profile/view/5191862_1\"> Marin and Barrett, Inc. </a><span class=\"pp_card_street\"> 127 Dorrance Street </span><span class=\"pp_card_street\"><span>Providence</span>, <span>RI</span><span> 02903 </span></span><span class=\"pp_card_street\"> 401-519-6800 </span></p><p><a href=\"/profile/view/5222606_1\"> Marin and Barrett, Inc. </a><span class=\"pp_card_street\"> 3 Broad St </span><span class=\"pp_card_street\"> Suite 205 </span><span class=\"pp_card_street\"><span>Charleston</span>, <span>SC</span><span> 29401 </span></span><span class=\"pp_card_street\"> 843-642-2449 </span></p>"
        }
    ],
    "practiceAreas": "Personal Injury 100%",
    "litigation": "<ul><li>100%</li></ul>",
    "languages": "",
    "classesAndSeminars": "",
    "offersFreeInitialConsultation": "Yes",
    "officeHours": "<p> 24 x 7 <br></p>",
    "honors": "",
    "articles": "",
    "social_fb": "",
    "social_twitter": "",
    "social_linkedin": "",
    "social_instagram": "",
    "scrapeUrl": "https://lawyers.findlaw.com/profile/view/5201500_1?refPageViewId=6bb1b917d24d370d#",
    "description": "<p>Marin and Barrett, Inc. is a personal injury firm located in Woodbridge, Connecticut serving clients throughout Connecticut. Our team of Connecticut personal injury attorneys and legal professionals fully understand the rights of accident victims under Connecticut law...</p>"
}